{
    "key": "group_6044f32f478ab",
    "title": "c-FullWidthQuote",
    "fields": [
        {
            "key": "field_6044f3448d1ad",
            "label": "Text",
            "name": "text",
            "type": "textarea",
            "instructions": "",
            "required": 0,
            "conditional_logic": 0,
            "wrapper": {
                "width": "",
                "class": "",
                "id": ""
            },
            "default_value": "",
            "placeholder": "",
            "maxlength": "",
            "rows": 3,
            "new_lines": ""
        }
    ],
    "location": [],
    "menu_order": 0,
    "position": "normal",
    "style": "default",
    "label_placement": "top",
    "instruction_placement": "label",
    "hide_on_screen": "",
    "active": true,
    "description": "",
    "is_acf_component": 1,
    "acf_component_defaults": {
        "repeatable": "0",
        "min": "",
        "max": "",
        "layout": "block",
        "button_label": "",
        "appearances": ""
    },
    "modified": 1615131481
}